{
    "weather_preferences":  {
                                "humidity":  {
                                                 "min":  57,
                                                 "max":  85
                                             },
                                "temperature":  {
                                                    "min":  13,
                                                    "max":  31
                                                }
                            },
    "amendments":  [
                       "Compost",
                       "Manure",
                       "Lime"
                   ],
    "name":  "Soil120"
}
