{
    "weather_preferences":  {
                                "humidity":  {
                                                 "min":  45,
                                                 "max":  70
                                             },
                                "temperature":  {
                                                    "min":  18,
                                                    "max":  31
                                                }
                            },
    "affected_crops":  [
                           "Crop165",
                           "Crop184"
                       ],
    "name":  "Disease16"
}
