{
    "weather_preferences":  {
                                "humidity":  {
                                                 "min":  43,
                                                 "max":  68
                                             },
                                "temperature":  {
                                                    "min":  12,
                                                    "max":  23
                                                }
                            },
    "affected_crops":  [
                           "Crop11",
                           "Crop181"
                       ],
    "name":  "Disease33"
}
