{
    "weather_preferences":  {
                                "humidity":  {
                                                 "min":  41,
                                                 "max":  71
                                             },
                                "temperature":  {
                                                    "min":  8,
                                                    "max":  28
                                                }
                            },
    "name":  "Pest77",
    "controls":  [
                     "Pheromone Traps",
                     "Soap Spray",
                     "Insecticide"
                 ]
}
